SideValidator/__init__.py
sidevalidator-1.0.1.dist-info/LICENSE
sidevalidator-1.0.1.dist-info/METADATA
sidevalidator-1.0.1.dist-info/WHEEL
sidevalidator-1.0.1.dist-info/RECORD
