Metadata-Version: 2.3
Name: SideValidator
Version: 1.0.1
Summary: Add some Qt input validator.
License: MIT
Keywords: Qt,Site,Easy,Validator
Author: qiufeng
Author-email: appleidqiufeng@outlook.com
Requires-Python: >=3.8,<4.0
Classifier: License :: OSI Approved :: MIT License
Classifier: Operating System :: OS Independent
Classifier: Programming Language :: Python :: 3
Classifier: Programming Language :: Python :: 3.8
Classifier: Programming Language :: Python :: 3.9
Classifier: Programming Language :: Python :: 3.10
Classifier: Programming Language :: Python :: 3.11
Classifier: Programming Language :: Python :: 3.12
Classifier: Programming Language :: Python :: 3.13
Requires-Dist: PySide6 (>=6.0,<7.0)
Project-URL: Changelog, https://github.com/qiufengcute/SideValidator/blob/main/CHANGELOG.md
Project-URL: Homepage, https://github.com/qiufengcute/SideValidator
Project-URL: Repository, https://github.com/qiufengcute/SideValidator
